bsonrpc/exceptions.py
bsonrpc/util.py
bsonrpc/definitions.py
bsonrpc/misc.py
bsonrpc/dispatcher.py
bsonrpc/__init__.py
bsonrpc/socket_queue.py
bsonrpc/framing.py
bsonrpc/rpc.py
bsonrpc/options.py
bsonrpc/concurrent.py
bsonrpc/interfaces.py
bsonrpc-0.1.2.dist-info/METADATA
bsonrpc-0.1.2.dist-info/top_level.txt
bsonrpc-0.1.2.dist-info/RECORD
bsonrpc-0.1.2.dist-info/DESCRIPTION.rst
bsonrpc-0.1.2.dist-info/WHEEL
bsonrpc-0.1.2.dist-info/metadata.json
